Metadata-Version: 2.1
Name: Kqlmagic
Version: 0.1.114.post26
Summary: Kqlmagic: Microsoft Azure Monitor magic extension to Jupyter notebook
Home-page: https://github.com/Microsoft/jupyter-Kqlmagic
Author: Michael Binshtock
Author-email: michabin@microsoft.com
Maintainer: Michael Binshtock
Maintainer-email: michabin@microsoft.com
License: MIT License
Project-URL: Documentation, https://github.com/microsoft/jupyter-Kqlmagic/blob/master/README.md
Project-URL: Source, https://github.com/microsoft/jupyter-Kqlmagic
Keywords: database ipython jupyter jupyterlab jupyter-notebook nteract azureml query language kql adx azure-data-explorer kusto loganalytics applicationinsights aria
Classifier: Development Status :: 5 - Production/Stable
Classifier: Intended Audience :: Developers
Classifier: Intended Audience :: System Administrators
Classifier: Intended Audience :: Customer Service
Classifier: Intended Audience :: Information Technology
Classifier: Intended Audience :: Science/Research
Classifier: Environment :: Console
Classifier: Environment :: Plugins
Classifier: License :: OSI Approved :: MIT License
Classifier: Natural Language :: English
Classifier: Topic :: Database
Classifier: Topic :: Database :: Front-Ends
Classifier: Framework :: IPython
Classifier: Framework :: Jupyter
Classifier: Operating System :: OS Independent
Classifier: Programming Language :: Python :: 3.6
Classifier: Programming Language :: Python :: 3.7
Classifier: Programming Language :: Python :: 3.8
Classifier: Programming Language :: Python :: 3.9
Classifier: Programming Language :: Python :: 3.10
Classifier: Programming Language :: Python :: 3.11
Classifier: Programming Language :: Python :: 3 :: Only
Requires-Python: >=3.6
License-File: LICENSE.TXT
License-File: NOTICE.TXT
Requires-Dist: psutil >=5.4.7
Requires-Dist: flask >=1.0.3
Requires-Dist: plotly >=3.10.0
Requires-Dist: cryptography >=2.7
Requires-Dist: azure-common >=1.1.25
Requires-Dist: msal-extensions >=0.3.0
Requires-Dist: pandas >=0.23.4
Requires-Dist: Pygments >=2.2.0
Requires-Dist: requests >=2.21.0
Requires-Dist: Markdown >=3.0.1
Requires-Dist: azure-identity >=1.5.0
Requires-Dist: ipywidgets
Requires-Dist: ipython >=7.1.1
Requires-Dist: prettytable >=0.7.2
Requires-Dist: matplotlib >=3.0.0
Requires-Dist: python-dateutil >=2.7.5
Requires-Dist: msrestazure >=0.6.3
Requires-Dist: isodate >=0.6.0
Requires-Dist: pyperclip >=1.7.0
Requires-Dist: dummy-notebookutils >=1.5.1
Requires-Dist: msal >=1.11.0
Requires-Dist: password-strength >=0.0.3
Requires-Dist: beautifulsoup4 >=4.6.3
Requires-Dist: lxml >=4.2.5
Requires-Dist: ipykernel >=5.1.1
Requires-Dist: traitlets >=4.3.2
Requires-Dist: setuptools >=41.0.1
Provides-Extra: dev
Requires-Dist: twine ; extra == 'dev'
Requires-Dist: pip ; extra == 'dev'
Requires-Dist: wheel ; extra == 'dev'
Requires-Dist: black ; extra == 'dev'
Requires-Dist: flake8 ; extra == 'dev'
Requires-Dist: pipreqs ; extra == 'dev'
Requires-Dist: mccabe ; extra == 'dev'
Requires-Dist: pep8autopep8 ; extra == 'dev'
Requires-Dist: pydocstyle ; extra == 'dev'
Provides-Extra: tests
Requires-Dist: pytest ; extra == 'tests'
Requires-Dist: pytest-pep8 ; extra == 'tests'
Requires-Dist: pytest-docstyle ; extra == 'tests'
Requires-Dist: pytest-flakes ; extra == 'tests'
Requires-Dist: pytest-cov ; extra == 'tests'
Requires-Dist: QtPy ; extra == 'tests'
Requires-Dist: PyQt5 ; extra == 'tests'
